fountain_tools/__init__.py
fountain_tools/callback_parser.py
fountain_tools/format_helper.py
fountain_tools/fountain.py
fountain_tools/parser.py
fountain_tools/writer.py
fountain_tools-0.0.7.dist-info/METADATA
fountain_tools-0.0.7.dist-info/WHEEL
fountain_tools-0.0.7.dist-info/top_level.txt
fountain_tools-0.0.7.dist-info/RECORD
