Metadata-Version: 2.4
Name: fountain-tools
Version: 0.0.7
Summary: Utils for the Fountain scriptwriting format.
Author-email: wildwinter <ian@wildwinter.net>
Project-URL: Homepage, https://github.com/wildwinter/fountain-tools
Project-URL: Bug Tracker, https://github.com/wildwinter/fountain-tools/issues
Keywords: fountain,script,parser
Classifier: Programming Language :: Python :: 3
Classifier: License :: OSI Approved :: MIT License
Classifier: Operating System :: OS Independent
Requires-Python: >=3.7
